{
    "rules": {
        "1729669868469-531k4": {
            "id": "1729669868469-531k4",
            "name": "おみくじ",
            "switch": 1,
            "disabledIds": [],
            "matchExact": [],
            "matchStartsWith": [],
            "matchIncludes": []
        }
    },
    "omikuji": {
        "1729669848759-a4czl": {
            "id": "1729669848759-a4czl",
            "name": "大吉",
            "weight": 1,
            "threshold": {
                "isSyoken": false,
                "time": {
                    "isEnabled": false,
                    "value1": 0,
                    "value2": 0
                },
                "elapsed": {
                    "isEnabled": false,
                    "unit": "hour",
                    "comparison": "max",
                    "value1": 0,
                    "value2": 0
                },
                "count": {
                    "isEnabled": false,
                    "unit": "no",
                    "comparison": "max",
                    "value1": 0,
                    "value2": 0
                },
                "gift": {
                    "isEnabled": false,
                    "comparison": "max",
                    "value1": 0,
                    "value2": 0
                }
            },
            "post": [
                {
                    "type": "onecomme",
                    "botKey": "reimu",
                    "iconKey": "Default",
                    "delaySeconds": 0,
                    "content": "<<user>>さんの運勢は【大吉】<<random>>"
                }
            ]
        }
    },
    "place": {
    },
    "rulesOrder": [
        "1729669868469-531k4"
    ],
    "omikujiOrder": [
        "1729669848759-a4czl"
    ],
    "placeOrder": [
    ],
    "preferences": {
        "basicDelay": 1,
        "omikujiCooldown": 2,
        "commentDuration": 5,
        "BotUserIDname": "FirstCounter"
    }
}